smartblinds_client/__init__.py
smartblinds_client/smartblinds.py
smartblinds_client-0.6.dist-info/LICENSE
smartblinds_client-0.6.dist-info/METADATA
smartblinds_client-0.6.dist-info/WHEEL
smartblinds_client-0.6.dist-info/top_level.txt
smartblinds_client-0.6.dist-info/RECORD
