Metadata-Version: 2.1
Name: smartblinds-client
Version: 0.6
Summary: Unofficial client for the MySmartBlinds Smart Bridge
Home-page: http://github.com/ianlevesque/smartblinds-client
Author: Ian Levesque
Author-email: ian@ianlevesque.org
License: UNKNOWN
Platform: UNKNOWN
Classifier: Development Status :: 4 - Beta
Classifier: Intended Audience :: Developers
Classifier: License :: OSI Approved :: MIT License
Classifier: Operating System :: OS Independent
Classifier: Programming Language :: Python
Requires-Dist: auth0-python
Requires-Dist: requests
